odoo/addons/l10n_br_website_sale_delivery/README.rst
odoo/addons/l10n_br_website_sale_delivery/__init__.py
odoo/addons/l10n_br_website_sale_delivery/__manifest__.py
odoo/addons/l10n_br_website_sale_delivery/i18n/l10n_br_website_sale_delivery.pot
odoo/addons/l10n_br_website_sale_delivery/i18n/pt_BR.po
odoo/addons/l10n_br_website_sale_delivery/models/__init__.py
odoo/addons/l10n_br_website_sale_delivery/models/sale_order.py
odoo/addons/l10n_br_website_sale_delivery/readme/CONFIGURE.rst
odoo/addons/l10n_br_website_sale_delivery/readme/CONTRIBUTORS.rst
odoo/addons/l10n_br_website_sale_delivery/readme/DESCRIPTION.rst
odoo/addons/l10n_br_website_sale_delivery/readme/HISTORY.rst
odoo/addons/l10n_br_website_sale_delivery/readme/INSTALL.rst
odoo/addons/l10n_br_website_sale_delivery/readme/ROADMAP.rst
odoo/addons/l10n_br_website_sale_delivery/readme/USAGE.rst
odoo/addons/l10n_br_website_sale_delivery/static/description/icon.png
odoo/addons/l10n_br_website_sale_delivery/static/description/index.html
odoo/addons/l10n_br_website_sale_delivery/static/src/js/l10n_br_website_sale_delivery_tour.js
odoo/addons/l10n_br_website_sale_delivery/tests/__init__.py
odoo/addons/l10n_br_website_sale_delivery/tests/test_website_sale_tour.py
odoo/addons/l10n_br_website_sale_delivery/views/assets.xml
odoo14_addon_l10n_br_website_sale_delivery-14.0.1.0.2.dist-info/METADATA
odoo14_addon_l10n_br_website_sale_delivery-14.0.1.0.2.dist-info/WHEEL
odoo14_addon_l10n_br_website_sale_delivery-14.0.1.0.2.dist-info/top_level.txt
odoo14_addon_l10n_br_website_sale_delivery-14.0.1.0.2.dist-info/RECORD
