Metadata-Version: 2.1
Name: odoo14-addon-l10n_br_website_sale_delivery
Version: 14.0.1.0.2
Summary: Implements Brazilian freight values for delivery.
Home-page: https://github.com/OCA/l10n-brazil
Author: KMEE,Odoo Community Association (OCA)
Author-email: support@odoo-community.org
License: AGPL-3
Classifier: Programming Language :: Python
Classifier: Framework :: Odoo
Classifier: Framework :: Odoo :: 14.0
Classifier: License :: OSI Approved :: GNU Affero General Public License v3
Classifier: Development Status :: 3 - Alpha
Requires-Python: >=3.6
Requires-Dist: odoo14-addon-l10n-br-delivery
Requires-Dist: odoo14-addon-l10n-br-website-sale
Requires-Dist: odoo<14.1dev,>=14.0a
